actinet/__init__.py
actinet/_version.py
actinet/accPlot.py
actinet/actinet.py
actinet/circadian.py
actinet/evaluate.py
actinet/hmm.py
actinet/models.py
actinet/prepare.py
actinet/sslmodel.py
actinet/summarisation.py
actinet/utils/__init__.py
actinet/utils/collate_outputs.py
actinet/utils/eval_utils.py
actinet/utils/generate_commands.py
actinet/utils/sleep_utils.py
actinet/utils/summary_utils.py
actinet/utils/utils.py
actinet-0.5.2.dist-info/licenses/LICENSE.md
actinet-0.5.2.dist-info/METADATA
actinet-0.5.2.dist-info/WHEEL
actinet-0.5.2.dist-info/entry_points.txt
actinet-0.5.2.dist-info/top_level.txt
actinet-0.5.2.dist-info/RECORD
